saibyo/__init__.py
saibyo/base/__init__.py
saibyo/base/conf/__init__.py
saibyo/base/conf/app.py
saibyo/base/conf/schema.py
saibyo/base/constants/__init__.py
saibyo/base/constants/app.py
saibyo/base/logs/__init__.py
saibyo/base/logs/logger.py
saibyo/cli/__init__.py
saibyo/cli/compare.py
saibyo/cli/interpolate.py
saibyo/cli/main.py
saibyo/conf/__init__.py
saibyo/conf/conf.py
saibyo/constants/__init__.py
saibyo/constants/app.py
saibyo/constants/conf.py
saibyo/core/__init__.py
saibyo/core/comparation/__init__.py
saibyo/core/comparation/comparator.py
saibyo/core/interpolation/__init__.py
saibyo/core/interpolation/interpolator.py
saibyo/core/interpolation/rife.py
saibyo/core/io/__init__.py
saibyo/core/io/video.py
saibyo/engine/__init__.py
saibyo/engine/comparation/__init__.py
saibyo/engine/comparation/engine.py
saibyo/engine/interpolation/__init__.py
saibyo/engine/interpolation/base.py
saibyo/engine/interpolation/engine.py
saibyo/engine/interpolation/rife.py
saibyo/engine/interpolation/weights/__init__.py
saibyo/engine/interpolation/weights/flownet.pkl
saibyo/metadata/__init__.py
saibyo/metadata/video.py
saibyo/modules/__init__.py
saibyo/modules/comparation/__init__.py
saibyo/modules/comparation/canvas.py
saibyo/modules/interpolation/__init__.py
saibyo/modules/interpolation/ifnet.py
saibyo/utils/__init__.py
saibyo/utils/comparation/__init__.py
saibyo/utils/comparation/color.py
saibyo/utils/comparation/frame.py
saibyo/utils/interpolation/__init__.py
saibyo/utils/interpolation/audio.py
saibyo/utils/interpolation/image.py
saibyo/utils/interpolation/msssim.py
saibyo-0.14.0.dist-info/licenses/LICENSE
saibyo-0.14.0.dist-info/METADATA
saibyo-0.14.0.dist-info/WHEEL
saibyo-0.14.0.dist-info/top_level.txt
saibyo-0.14.0.dist-info/RECORD
