Metadata-Version: 2.4
Name: saibyo
Version: 0.14.0
Summary: A Python package for video interpolation using deep learning.
Author: Alvaro Rodriguez
License: MIT License
Requires-Python: >=3.10
License-File: LICENSE
Requires-Dist: ipykernel>=6.29.5
Requires-Dist: torch>=2.6.0
Requires-Dist: torchvision>=0.21.0
Requires-Dist: torchaudio>=2.6.0
Requires-Dist: opencv-python>=4.11.0.86
Requires-Dist: matplotlib>=3.10.0
Requires-Dist: av>=14.1.0
Requires-Dist: pymediainfo>=6.1.0
Requires-Dist: tqdm>=4.67.1
Requires-Dist: pydantic>=2.10.6
Requires-Dist: fire>=0.7.0
Requires-Dist: pydantic-settings>=2.7.1
Requires-Dist: attrs>=25.3.0
Requires-Dist: ffmpeg-python>=0.2.0
Provides-Extra: format
Requires-Dist: ruff>=0.1.14; extra == "format"
Provides-Extra: test
Requires-Dist: pytest>=7.4.4; extra == "test"
Requires-Dist: pytest-cov>=4.1.0; extra == "test"
Requires-Dist: faker>=24.8.0; extra == "test"
Requires-Dist: httpx>=0.27.0; extra == "test"
Provides-Extra: publish
Requires-Dist: uv; extra == "publish"
Requires-Dist: tomli; extra == "publish"
Requires-Dist: build; extra == "publish"
Dynamic: license-file
